nbxsync/__init__.py
nbxsync/navigation.py
nbxsync/settings.py
nbxsync/template_content.py
nbxsync/urls.py
nbxsync/worker.py
nbxsync/api/__init__.py
nbxsync/api/urls.py
nbxsync/api/serializers/__init__.py
nbxsync/api/serializers/sync_info.py
nbxsync/api/serializers/zabbixconfigurationgroup.py
nbxsync/api/serializers/zabbixconfigurationgroupassignment.py
nbxsync/api/serializers/zabbixhostgroup.py
nbxsync/api/serializers/zabbixhostgroupassignment.py
nbxsync/api/serializers/zabbixhostinterface.py
nbxsync/api/serializers/zabbixhostinventory.py
nbxsync/api/serializers/zabbixmacro.py
nbxsync/api/serializers/zabbixmacroassignment.py
nbxsync/api/serializers/zabbixmaintenance.py
nbxsync/api/serializers/zabbixmaintenanceobjectassignment.py
nbxsync/api/serializers/zabbixmaintenanceperiod.py
nbxsync/api/serializers/zabbixmaintenancetagassignment.py
nbxsync/api/serializers/zabbixproxy.py
nbxsync/api/serializers/zabbixproxygroup.py
nbxsync/api/serializers/zabbixserver.py
nbxsync/api/serializers/zabbixserverassignment.py
nbxsync/api/serializers/zabbixtag.py
nbxsync/api/serializers/zabbixtagassignment.py
nbxsync/api/serializers/zabbixtemplate.py
nbxsync/api/serializers/zabbixtemplateassignment.py
nbxsync/api/views/__init__.py
nbxsync/api/views/zabbixconfigurationgroup.py
nbxsync/api/views/zabbixconfigurationgroupassignment.py
nbxsync/api/views/zabbixhostgroup.py
nbxsync/api/views/zabbixhostgroupassignment.py
nbxsync/api/views/zabbixhostinterface.py
nbxsync/api/views/zabbixhostinventory.py
nbxsync/api/views/zabbixmacro.py
nbxsync/api/views/zabbixmacroassignment.py
nbxsync/api/views/zabbixmaintenance.py
nbxsync/api/views/zabbixmaintenanceobjectassignment.py
nbxsync/api/views/zabbixmaintenanceperiod.py
nbxsync/api/views/zabbixmaintenancetagassignment.py
nbxsync/api/views/zabbixproxy.py
nbxsync/api/views/zabbixproxygroup.py
nbxsync/api/views/zabbixserver.py
nbxsync/api/views/zabbixserverassignment.py
nbxsync/api/views/zabbixtag.py
nbxsync/api/views/zabbixtagassignment.py
nbxsync-1.0.2.dist-info/licenses/LICENSE
nbxsync-1.0.2.dist-info/METADATA
nbxsync-1.0.2.dist-info/WHEEL
nbxsync-1.0.2.dist-info/top_level.txt
nbxsync-1.0.2.dist-info/RECORD
