Metadata-Version: 2.4
Name: nbxsync
Version: 1.0.2
Summary: nbxsync
Author-email: Opensource ICT Solutions <info@oicts.com>
License:                     GNU AFFERO GENERAL PUBLIC LICENSE
Project-URL: Homepage, https://nbxsync.com
Project-URL: Source, https://github.com/OpensourceICTSolutions/nbxsync
Project-URL: Bug Tracker, https://github.com/OpensourceICTSolutions/nbxsync/issues/
Keywords: netbox,netbox-plugin,zabbix,nbxsync
Classifier: Programming Language :: Python :: 3
Classifier: Operating System :: OS Independent
Requires-Python: >=3.10
License-File: LICENSE
Requires-Dist: zabbix_utils
Requires-Dist: pydantic<2.11
Provides-Extra: dev
Requires-Dist: ruff; extra == "dev"
Requires-Dist: djlint; extra == "dev"
Requires-Dist: mkdocs-material; extra == "dev"
Dynamic: license-file
